Sample_package/__init__.py
Sample_package/calculator.py
calculator_talha44220-0.1.1.dist-info/licenses/LICENSE
calculator_talha44220-0.1.1.dist-info/METADATA
calculator_talha44220-0.1.1.dist-info/WHEEL
calculator_talha44220-0.1.1.dist-info/top_level.txt
calculator_talha44220-0.1.1.dist-info/RECORD
