Metadata-Version: 2.4
Name: calculator_talha44220
Version: 0.1.1
Summary: A simple calculator package for basic arithmetic operations
Author-email: Muhammad Talha Aslam <talha.aslam591@gmail.com>
License: MIT
Project-URL: Homepage, https://github.com/yourusername/simple-calculator
Project-URL: Bug Reports, https://github.com/yourusername/simple-calculator/issues
Project-URL: Source, https://github.com/yourusername/simple-calculator
Keywords: calculator,math,arithmetic,simple
Classifier: Development Status :: 3 - Alpha
Classifier: Intended Audience :: Developers
Classifier: License :: OSI Approved :: MIT License
Classifier: Operating System :: OS Independent
Classifier: Programming Language :: Python :: 3
Classifier: Programming Language :: Python :: 3.6
Classifier: Programming Language :: Python :: 3.7
Classifier: Programming Language :: Python :: 3.8
Classifier: Programming Language :: Python :: 3.9
Classifier: Programming Language :: Python :: 3.10
Classifier: Programming Language :: Python :: 3.11
Classifier: Topic :: Software Development :: Libraries :: Python Modules
Classifier: Topic :: Scientific/Engineering :: Mathematics
Requires-Python: >=3.6
License-File: LICENSE
Dynamic: license-file
